{"index":{"links":{"/":[{"source":"/","target":"/psychology","text":"Психология"},{"source":"/","target":"/piano","text":"Клавиши"}],"/piano":[{"source":"/piano","target":"/piano/keyboard","text":"Клавиатура"}],"/piano/keyboard":[{"source":"/piano/keyboard","target":"/piano/octave","text":"октавами"}],"/piano/octave":[{"source":"/piano/octave","target":"/piano/note","text":"ноту"}],"/psychology":[{"source":"/psychology","target":"/psychology/cbt","text":"Когнитивно-Поведенческая Терапия"},{"source":"/psychology","target":"/psychology/sdvg","text":"Конспект по вебинару о СДВГ"}],"/psychology/cbt":[{"source":"/psychology/cbt","target":"/psychology/cbt/personality","text":"Личность с точки зрения КПТ"},{"source":"/psychology/cbt","target":"/psychology/cbt/abcde","text":"Таблица ABCDE"},{"source":"/psychology/cbt","target":"/psychology/cbt/conceptualization","text":"Концептуализация"}],"/psychology/cbt/abcde":[{"source":"/psychology/cbt/abcde","target":"/psychology/cbt/abcde/activating_event","text":"Событие"},{"source":"/psychology/cbt/abcde","target":"/psychology/cbt/abcde/autothoughts","text":"Автомысли"},{"source":"/psychology/cbt/abcde","target":"/psychology/cbt/abcde/consequences","text":"Последствия"},{"source":"/psychology/cbt/abcde","target":"/psychology/cbt/abcde/disputation","text":"Диспут"},{"source":"/psychology/cbt/abcde","target":"/psychology/cbt/abcde/efficient","text":"Вывод"}],"/psychology/cbt/abcde/autothoughts":[{"source":"/psychology/cbt/abcde/autothoughts","target":"/psychology/cbt/core_belief","text":"глубинное убеждение"}],"/psychology/cbt/abcde/consequences":[{"source":"/psychology/cbt/abcde/consequences","target":"/psychology/cbt/abcde/consequence/emotional","text":"Эмоциональные"},{"source":"/psychology/cbt/abcde/consequences","target":"/psychology/cbt/abcde/consequence/behavior","text":"Поведенческие"},{"source":"/psychology/cbt/abcde/consequences","target":"/psychology/cbt/abcde/consequence/physiological","text":"Физиологические"},{"source":"/psychology/cbt/abcde/consequences","target":"/psychology/cbt/abcde/consequence/cognitive","text":"Когнитивные"}],"/psychology/cbt/childhood_event":[{"source":"/psychology/cbt/childhood_event","target":"/psychology/cbt/core_belief","text":"глубинное убеждение"}],"/psychology/cbt/core_belief":[{"source":"/psychology/cbt/core_belief","target":"/psychology/cbt/core_belief_category","text":"Категории глубинных убеждений"},{"source":"/psychology/cbt/core_belief","target":"/psychology/cbt/related_rule","text":"сопутствующие правила"}],"/psychology/cbt/core_belief_category":[{"source":"/psychology/cbt/core_belief_category","target":"/psychology/cbt/core_belief_category/incompetence","text":"Некомпетентность"},{"source":"/psychology/cbt/core_belief_category","target":"/psychology/cbt/core_belief_category/unattractiveness","text":"Непривлекательность"},{"source":"/psychology/cbt/core_belief_category","target":"/psychology/cbt/core_belief_category/worthlessness","text":"Никчёмность"}],"/psychology/cbt/personality":[{"source":"/psychology/cbt/personality","target":"/psychology/cbt/childhood_event","text":"событие из детства"}],"/psychology/cbt/related_rule":[{"source":"/psychology/cbt/related_rule","target":"/psychology/cbt/behavior_strategy","text":"стратегия поведения"}],"/psychology/emotions/anxiety":[{"source":"/psychology/emotions/anxiety","target":"/psychology/cbt/abcde/activating_event","text":"триггер"},{"source":"/psychology/emotions/anxiety","target":"/psychology/cbt/abcde/autothoughts","text":"автоматическая мысль"}],"/psychology/sdvg":[{"source":"/psychology/sdvg","target":"/psychology/emotions/anxiety","text":"Тревога"},{"source":"/psychology/sdvg","target":"/psychology/sdvg/anxiety_reasons","text":"причин"},{"source":"/psychology/sdvg","target":"/psychology/sdvg/anxiety_type","text":"типы тревоги"},{"source":"/psychology/sdvg","target":"/psychology/sdvg/anxiety_normal","text":"да и не нужно"},{"source":"/psychology/sdvg","target":"/psychology/cbt/core_belief","text":"глубинных убеждений"},{"source":"/psychology/sdvg","target":"/psychology/emotions/panic_attack","text":"паническую атаку"},{"source":"/psychology/sdvg","target":"/psychology/sdvg/ocd","text":"ОКР"},{"source":"/psychology/sdvg","target":"/psychology/cbt/abcde/autothoughts","text":"Навязчивые мысли"},{"source":"/psychology/sdvg","target":"/psychology/sdvg/obsession","text":"замыкание"},{"source":"/psychology/sdvg","target":"/psychology/cbt","text":"КПТ"},{"source":"/psychology/sdvg","target":"/psychology/sdvg/relax","text":"релаксация по Джекобсону"},{"source":"/psychology/sdvg","target":"/psychology/cbt/abcde","text":"рационализация"},{"source":"/psychology/sdvg","target":"/psychology/sdvg/adhd","text":"СДВГ"}],"/psychology/sdvg/anxiety_normal":[{"source":"/psychology/sdvg/anxiety_normal","target":"/psychology/emotions/anxiety","text":"Тревога"}],"/psychology/sdvg/anxiety_reasons":[{"source":"/psychology/sdvg/anxiety_reasons","target":"/psychology/emotions/anxiety","text":"тревога"},{"source":"/psychology/sdvg/anxiety_reasons","target":"/psychology/cbt/core_belief","text":"Глубинное убеждение"}],"/psychology/sdvg/anxiety_type":[{"source":"/psychology/sdvg/anxiety_type","target":"/psychology/emotions/anxiety","text":"тревоги"}],"/psychology/sdvg/obsession":[{"source":"/psychology/sdvg/obsession","target":"/psychology/sdvg/ocd","text":"ОКР"}]},"backlinks":{"/piano":[{"source":"/","target":"/piano","text":"Клавиши"}],"/piano/keyboard":[{"source":"/piano","target":"/piano/keyboard","text":"Клавиатура"}],"/piano/note":[{"source":"/piano/octave","target":"/piano/note","text":"ноту"}],"/piano/octave":[{"source":"/piano/keyboard","target":"/piano/octave","text":"октавами"}],"/psychology":[{"source":"/","target":"/psychology","text":"Психология"}],"/psychology/cbt":[{"source":"/psychology/sdvg","target":"/psychology/cbt","text":"КПТ"},{"source":"/psychology","target":"/psychology/cbt","text":"Когнитивно-Поведенческая Терапия"}],"/psychology/cbt/abcde":[{"source":"/psychology/cbt","target":"/psychology/cbt/abcde","text":"Таблица ABCDE"},{"source":"/psychology/sdvg","target":"/psychology/cbt/abcde","text":"рационализация"}],"/psychology/cbt/abcde/activating_event":[{"source":"/psychology/cbt/abcde","target":"/psychology/cbt/abcde/activating_event","text":"Событие"},{"source":"/psychology/emotions/anxiety","target":"/psychology/cbt/abcde/activating_event","text":"триггер"}],"/psychology/cbt/abcde/autothoughts":[{"source":"/psychology/cbt/abcde","target":"/psychology/cbt/abcde/autothoughts","text":"Автомысли"},{"source":"/psychology/emotions/anxiety","target":"/psychology/cbt/abcde/autothoughts","text":"автоматическая мысль"},{"source":"/psychology/sdvg","target":"/psychology/cbt/abcde/autothoughts","text":"Навязчивые мысли"}],"/psychology/cbt/abcde/consequence/behavior":[{"source":"/psychology/cbt/abcde/consequences","target":"/psychology/cbt/abcde/consequence/behavior","text":"Поведенческие"}],"/psychology/cbt/abcde/consequence/cognitive":[{"source":"/psychology/cbt/abcde/consequences","target":"/psychology/cbt/abcde/consequence/cognitive","text":"Когнитивные"}],"/psychology/cbt/abcde/consequence/emotional":[{"source":"/psychology/cbt/abcde/consequences","target":"/psychology/cbt/abcde/consequence/emotional","text":"Эмоциональные"}],"/psychology/cbt/abcde/consequence/physiological":[{"source":"/psychology/cbt/abcde/consequences","target":"/psychology/cbt/abcde/consequence/physiological","text":"Физиологические"}],"/psychology/cbt/abcde/consequences":[{"source":"/psychology/cbt/abcde","target":"/psychology/cbt/abcde/consequences","text":"Последствия"}],"/psychology/cbt/abcde/disputation":[{"source":"/psychology/cbt/abcde","target":"/psychology/cbt/abcde/disputation","text":"Диспут"}],"/psychology/cbt/abcde/efficient":[{"source":"/psychology/cbt/abcde","target":"/psychology/cbt/abcde/efficient","text":"Вывод"}],"/psychology/cbt/behavior_strategy":[{"source":"/psychology/cbt/related_rule","target":"/psychology/cbt/behavior_strategy","text":"стратегия поведения"}],"/psychology/cbt/childhood_event":[{"source":"/psychology/cbt/personality","target":"/psychology/cbt/childhood_event","text":"событие из детства"}],"/psychology/cbt/conceptualization":[{"source":"/psychology/cbt","target":"/psychology/cbt/conceptualization","text":"Концептуализация"}],"/psychology/cbt/core_belief":[{"source":"/psychology/cbt/abcde/autothoughts","target":"/psychology/cbt/core_belief","text":"глубинное убеждение"},{"source":"/psychology/cbt/childhood_event","target":"/psychology/cbt/core_belief","text":"глубинное убеждение"},{"source":"/psychology/sdvg/anxiety_reasons","target":"/psychology/cbt/core_belief","text":"Глубинное убеждение"},{"source":"/psychology/sdvg","target":"/psychology/cbt/core_belief","text":"глубинных убеждений"}],"/psychology/cbt/core_belief_category":[{"source":"/psychology/cbt/core_belief","target":"/psychology/cbt/core_belief_category","text":"Категории глубинных убеждений"}],"/psychology/cbt/core_belief_category/incompetence":[{"source":"/psychology/cbt/core_belief_category","target":"/psychology/cbt/core_belief_category/incompetence","text":"Некомпетентность"}],"/psychology/cbt/core_belief_category/unattractiveness":[{"source":"/psychology/cbt/core_belief_category","target":"/psychology/cbt/core_belief_category/unattractiveness","text":"Непривлекательность"}],"/psychology/cbt/core_belief_category/worthlessness":[{"source":"/psychology/cbt/core_belief_category","target":"/psychology/cbt/core_belief_category/worthlessness","text":"Никчёмность"}],"/psychology/cbt/personality":[{"source":"/psychology/cbt","target":"/psychology/cbt/personality","text":"Личность с точки зрения КПТ"}],"/psychology/cbt/related_rule":[{"source":"/psychology/cbt/core_belief","target":"/psychology/cbt/related_rule","text":"сопутствующие правила"}],"/psychology/emotions/anxiety":[{"source":"/psychology/sdvg/anxiety_normal","target":"/psychology/emotions/anxiety","text":"Тревога"},{"source":"/psychology/sdvg/anxiety_reasons","target":"/psychology/emotions/anxiety","text":"тревога"},{"source":"/psychology/sdvg/anxiety_type","target":"/psychology/emotions/anxiety","text":"тревоги"},{"source":"/psychology/sdvg","target":"/psychology/emotions/anxiety","text":"Тревога"}],"/psychology/emotions/panic_attack":[{"source":"/psychology/sdvg","target":"/psychology/emotions/panic_attack","text":"паническую атаку"}],"/psychology/sdvg":[{"source":"/psychology","target":"/psychology/sdvg","text":"Конспект по вебинару о СДВГ"}],"/psychology/sdvg/adhd":[{"source":"/psychology/sdvg","target":"/psychology/sdvg/adhd","text":"СДВГ"}],"/psychology/sdvg/anxiety_normal":[{"source":"/psychology/sdvg","target":"/psychology/sdvg/anxiety_normal","text":"да и не нужно"}],"/psychology/sdvg/anxiety_reasons":[{"source":"/psychology/sdvg","target":"/psychology/sdvg/anxiety_reasons","text":"причин"}],"/psychology/sdvg/anxiety_type":[{"source":"/psychology/sdvg","target":"/psychology/sdvg/anxiety_type","text":"типы тревоги"}],"/psychology/sdvg/obsession":[{"source":"/psychology/sdvg","target":"/psychology/sdvg/obsession","text":"замыкание"}],"/psychology/sdvg/ocd":[{"source":"/psychology/sdvg/obsession","target":"/psychology/sdvg/ocd","text":"ОКР"},{"source":"/psychology/sdvg","target":"/psychology/sdvg/ocd","text":"ОКР"}],"/psychology/sdvg/relax":[{"source":"/psychology/sdvg","target":"/psychology/sdvg/relax","text":"релаксация по Джекобсону"}]}},"links":[{"source":"/","target":"/psychology","text":"Психология"},{"source":"/","target":"/piano","text":"Клавиши"},{"source":"/piano/keyboard","target":"/piano/octave","text":"октавами"},{"source":"/piano/octave","target":"/piano/note","text":"ноту"},{"source":"/piano","target":"/piano/keyboard","text":"Клавиатура"},{"source":"/psychology/cbt/abcde/autothoughts","target":"/psychology/cbt/core_belief","text":"глубинное убеждение"},{"source":"/psychology/cbt/abcde/consequences","target":"/psychology/cbt/abcde/consequence/emotional","text":"Эмоциональные"},{"source":"/psychology/cbt/abcde/consequences","target":"/psychology/cbt/abcde/consequence/behavior","text":"Поведенческие"},{"source":"/psychology/cbt/abcde/consequences","target":"/psychology/cbt/abcde/consequence/physiological","text":"Физиологические"},{"source":"/psychology/cbt/abcde/consequences","target":"/psychology/cbt/abcde/consequence/cognitive","text":"Когнитивные"},{"source":"/psychology/cbt/abcde","target":"/psychology/cbt/abcde/activating_event","text":"Событие"},{"source":"/psychology/cbt/abcde","target":"/psychology/cbt/abcde/autothoughts","text":"Автомысли"},{"source":"/psychology/cbt/abcde","target":"/psychology/cbt/abcde/consequences","text":"Последствия"},{"source":"/psychology/cbt/abcde","target":"/psychology/cbt/abcde/disputation","text":"Диспут"},{"source":"/psychology/cbt/abcde","target":"/psychology/cbt/abcde/efficient","text":"Вывод"},{"source":"/psychology/cbt/childhood_event","target":"/psychology/cbt/core_belief","text":"глубинное убеждение"},{"source":"/psychology/cbt/core_belief","target":"/psychology/cbt/core_belief_category","text":"Категории глубинных убеждений"},{"source":"/psychology/cbt/core_belief","target":"/psychology/cbt/related_rule","text":"сопутствующие правила"},{"source":"/psychology/cbt/core_belief_category","target":"/psychology/cbt/core_belief_category/incompetence","text":"Некомпетентность"},{"source":"/psychology/cbt/core_belief_category","target":"/psychology/cbt/core_belief_category/unattractiveness","text":"Непривлекательность"},{"source":"/psychology/cbt/core_belief_category","target":"/psychology/cbt/core_belief_category/worthlessness","text":"Никчёмность"},{"source":"/psychology/cbt/personality","target":"/psychology/cbt/childhood_event","text":"событие из детства"},{"source":"/psychology/cbt/related_rule","target":"/psychology/cbt/behavior_strategy","text":"стратегия поведения"},{"source":"/psychology/cbt","target":"/psychology/cbt/personality","text":"Личность с точки зрения КПТ"},{"source":"/psychology/cbt","target":"/psychology/cbt/abcde","text":"Таблица ABCDE"},{"source":"/psychology/cbt","target":"/psychology/cbt/conceptualization","text":"Концептуализация"},{"source":"/psychology/emotions/anxiety","target":"/psychology/cbt/abcde/activating_event","text":"триггер"},{"source":"/psychology/emotions/anxiety","target":"/psychology/cbt/abcde/autothoughts","text":"автоматическая мысль"},{"source":"/psychology/sdvg/anxiety_normal","target":"/psychology/emotions/anxiety","text":"Тревога"},{"source":"/psychology/sdvg/anxiety_reasons","target":"/psychology/emotions/anxiety","text":"тревога"},{"source":"/psychology/sdvg/anxiety_reasons","target":"/psychology/cbt/core_belief","text":"Глубинное убеждение"},{"source":"/psychology/sdvg/anxiety_type","target":"/psychology/emotions/anxiety","text":"тревоги"},{"source":"/psychology/sdvg/obsession","target":"/psychology/sdvg/ocd","text":"ОКР"},{"source":"/psychology/sdvg","target":"/psychology/emotions/anxiety","text":"Тревога"},{"source":"/psychology/sdvg","target":"/psychology/sdvg/anxiety_reasons","text":"причин"},{"source":"/psychology/sdvg","target":"/psychology/sdvg/anxiety_type","text":"типы тревоги"},{"source":"/psychology/sdvg","target":"/psychology/sdvg/anxiety_normal","text":"да и не нужно"},{"source":"/psychology/sdvg","target":"/psychology/cbt/core_belief","text":"глубинных убеждений"},{"source":"/psychology/sdvg","target":"/psychology/emotions/panic_attack","text":"паническую атаку"},{"source":"/psychology/sdvg","target":"/psychology/sdvg/ocd","text":"ОКР"},{"source":"/psychology/sdvg","target":"/psychology/cbt/abcde/autothoughts","text":"Навязчивые мысли"},{"source":"/psychology/sdvg","target":"/psychology/sdvg/obsession","text":"замыкание"},{"source":"/psychology/sdvg","target":"/psychology/cbt","text":"КПТ"},{"source":"/psychology/sdvg","target":"/psychology/sdvg/relax","text":"релаксация по Джекобсону"},{"source":"/psychology/sdvg","target":"/psychology/cbt/abcde","text":"рационализация"},{"source":"/psychology/sdvg","target":"/psychology/sdvg/adhd","text":"СДВГ"},{"source":"/psychology","target":"/psychology/cbt","text":"Когнитивно-Поведенческая Терапия"},{"source":"/psychology","target":"/psychology/sdvg","text":"Конспект по вебинару о СДВГ"}]}